online_store/__init__.py
online_store/__main__.py
online_store/main.py
online_store/order_management.py
online_store/setup.py
online_store/user_management.py
my_package_imba_lutaya_svo-0.1.0.dist-info/METADATA
my_package_imba_lutaya_svo-0.1.0.dist-info/WHEEL
my_package_imba_lutaya_svo-0.1.0.dist-info/entry_points.txt
my_package_imba_lutaya_svo-0.1.0.dist-info/top_level.txt
my_package_imba_lutaya_svo-0.1.0.dist-info/RECORD
