Metadata-Version: 2.1
Name: my-package-imba-lutaya-svo
Version: 0.1.0
Requires-Dist: requests
Requires-Dist: numpy
